{
    "/home": {
        "post": {
            "data": [
                {"id":1,"name": "Эспрессо", "cal": "9"},
                {"id":2,"name": "Латте", "cal": "130"},
                {"id":3,"name": "Капучинно", "cal": "61"},
                {"id":4,"name": "Бамбл", "cal": "35"},
                {"id":5,"name": "Лесной", "cal": "92"}
            ]
        },
        "get": {
            "data": [
                {"id":1,"name": "Эспрессо", "cal": "9"},
                {"id":2,"name": "Латте", "cal": "130"},
                {"id":3,"name": "Капучинно", "cal": "61"},
                {"id":4,"name": "Бамбл", "cal": "35"},
                {"id":5,"name": "Лесной", "cal": "92"}
            ]
        }
    }
}